odoo/addons/account_account_tag_code/README.rst
odoo/addons/account_account_tag_code/__init__.py
odoo/addons/account_account_tag_code/__manifest__.py
odoo/addons/account_account_tag_code/i18n/account_account_tag_code.pot
odoo/addons/account_account_tag_code/i18n/es.po
odoo/addons/account_account_tag_code/i18n/it.po
odoo/addons/account_account_tag_code/models/__init__.py
odoo/addons/account_account_tag_code/models/account_account_tag.py
odoo/addons/account_account_tag_code/readme/CONTRIBUTORS.md
odoo/addons/account_account_tag_code/readme/DESCRIPTION.md
odoo/addons/account_account_tag_code/static/description/icon.png
odoo/addons/account_account_tag_code/static/description/index.html
odoo/addons/account_account_tag_code/tests/__init__.py
odoo/addons/account_account_tag_code/tests/test_account_tag_display_name.py
odoo/addons/account_account_tag_code/views/account_account_tag_views.xml
odoo_addon_account_account_tag_code-17.0.1.0.0.2.dist-info/METADATA
odoo_addon_account_account_tag_code-17.0.1.0.0.2.dist-info/WHEEL
odoo_addon_account_account_tag_code-17.0.1.0.0.2.dist-info/top_level.txt
odoo_addon_account_account_tag_code-17.0.1.0.0.2.dist-info/RECORD
